{
    "users": [
        {
           "id" : 1,
           "name": "snikers",
           "surname": "twix",
           "photo_url": "https://www.snickers.com/sites/g/files/fnmzdf616/files/migrate-product-files/dryeqrv2efldaaoyceat.png",
           "balance": 700
        }
        {
           "id": 2,
           "name": "Modwq",
           "surname": "anikiev",
           "photo_url": "https://content2.rozetka.com.ua/goods/images/big/408089923.jpg",
           "balance": 7777
        } 
        {
            "id": 3,
            "name": "Snake",
            "surname": "Robocode",
            "photo_url": "https://vetmed.illinois.edu/wp-content/uploads/2022/06/Green-snake.jpg",
            "balance": 1500
        }
        {
            "id": 4,
            "name": "Dima",
            "surmane": "Robocode",
            "photo-url": "https://www.google.com/logos/fnbx/snake_arcade/cta_alt.png",
            "balance": 1000
        } 
        {
            "id": 5,
            "name": "Vasya",
            "surname": "Karburator",
            "photo_url": "nema",
            "balance": "780"
        }
    ],
    "products": [
        {
            "name": "TV",
            "brand": "LG",
            "price": 1000
        }
        {
            "name": "15 aphone",
            "brand": "Apple",
            "price": 666
        }    
        {
            "name": "Iphone",
            "brand": "Apple",
            "price": 1488
        }
        {
            "name": "vozduh",
            "brand": "naebalovo.com.ne.scam.nananananadorogi",
            "price": "19999999999999999.99$"
        }
        {       
            "name": "personazh",
            "brand": "kontra",
            "price": 1337
        }
    ]
}
